pbcgraph/__about__.py
pbcgraph/__init__.py
pbcgraph/component.py
pbcgraph/alg/__init__.py
pbcgraph/alg/_canonical_lift.py
pbcgraph/alg/_lift_patch.py
pbcgraph/alg/_neighbors.py
pbcgraph/alg/components.py
pbcgraph/alg/lattice.py
pbcgraph/alg/lift.py
pbcgraph/alg/paths.py
pbcgraph/core/__init__.py
pbcgraph/core/constants.py
pbcgraph/core/exceptions.py
pbcgraph/core/ordering.py
pbcgraph/core/protocols.py
pbcgraph/core/types.py
pbcgraph/graph/__init__.py
pbcgraph/graph/directed.py
pbcgraph/graph/multidirected.py
pbcgraph/graph/multigraph.py
pbcgraph/graph/shared.py
pbcgraph/graph/undirected.py
pbcgraph/lattice/__init__.py
pbcgraph/lattice/snf.py
pbcgraph-0.1.3.dist-info/METADATA
pbcgraph-0.1.3.dist-info/WHEEL
pbcgraph-0.1.3.dist-info/licenses/COPYING
pbcgraph-0.1.3.dist-info/licenses/LICENSE
pbcgraph-0.1.3.dist-info/licenses/NOTICE
pbcgraph-0.1.3.dist-info/RECORD
