Metadata-Version: 2.4
Name: pbcgraph
Version: 0.1.3
Summary: Translation-labeled periodic graphs on Z^d with exact component lattice invariants.
Project-URL: Homepage, https://github.com/IvanChernyshov/pbcgraph
Project-URL: Documentation, https://IvanChernyshov.github.io/pbcgraph
Project-URL: Repository, https://github.com/IvanChernyshov/pbcgraph
Project-URL: Issues, https://github.com/IvanChernyshov/pbcgraph/issues
Author-email: "Ivan Yu. Chernyshov" <ivan.chernyshoff@gmail.com>
License:                    GNU LESSER GENERAL PUBLIC LICENSE
License-File: COPYING
License-File: LICENSE
License-File: NOTICE
Keywords: crystallography,graph theory,lattice,networkx,periodic graphs,topology
Classifier: Development Status :: 3 - Alpha
Classifier: Intended Audience :: Science/Research
Classifier: License :: OSI Approved :: GNU Lesser General Public License v3 (LGPLv3)
Classifier: Operating System :: OS Independent
Classifier: Programming Language :: Python :: 3
Classifier: Programming Language :: Python :: 3 :: Only
Classifier: Topic :: Scientific/Engineering
Classifier: Topic :: Scientific/Engineering :: Chemistry
Classifier: Topic :: Scientific/Engineering :: Mathematics
Classifier: Topic :: Software Development :: Libraries
Requires-Python: >=3.10
Requires-Dist: networkx>=3.2
Requires-Dist: numpy>=1.23
Provides-Extra: dev
Requires-Dist: flake8>=7.0; extra == 'dev'
Requires-Dist: pytest>=8.0; extra == 'dev'
Provides-Extra: docs
Requires-Dist: griffe>=0.47; extra == 'docs'
Requires-Dist: ipykernel>=6.29; extra == 'docs'
Requires-Dist: jupyter>=1.0; extra == 'docs'
Requires-Dist: mkdocs-autorefs>=1.0; extra == 'docs'
Requires-Dist: mkdocs-jupyter>=0.21; extra == 'docs'
Requires-Dist: mkdocs-material>=9.5; extra == 'docs'
Requires-Dist: mkdocs>=1.6; extra == 'docs'
Requires-Dist: mkdocstrings[python]>=0.26; extra == 'docs'
Requires-Dist: nbformat>=5.9; extra == 'docs'
Requires-Dist: pymdown-extensions>=10.0; extra == 'docs'
Requires-Dist: ruff>=0.6; extra == 'docs'
